oandapyV20/__init__.py
oandapyV20/exceptions.py
oandapyV20/oandapyV20.py
oandapyV20/contrib/__init__.py
oandapyV20/contrib/generic.py
oandapyV20/contrib/factories/__init__.py
oandapyV20/contrib/factories/history.py
oandapyV20/contrib/requests/__init__.py
oandapyV20/contrib/requests/baserequest.py
oandapyV20/contrib/requests/extensions.py
oandapyV20/contrib/requests/limitorder.py
oandapyV20/contrib/requests/marketorder.py
oandapyV20/contrib/requests/mitorder.py
oandapyV20/contrib/requests/onfill.py
oandapyV20/contrib/requests/positionclose.py
oandapyV20/contrib/requests/stoplossorder.py
oandapyV20/contrib/requests/stoporder.py
oandapyV20/contrib/requests/takeprofitorder.py
oandapyV20/contrib/requests/tradeclose.py
oandapyV20/contrib/requests/trailingstoplossorder.py
oandapyV20/definitions/__init__.py
oandapyV20/definitions/accounts.py
oandapyV20/definitions/instruments.py
oandapyV20/definitions/orders.py
oandapyV20/definitions/pricing.py
oandapyV20/definitions/primitives.py
oandapyV20/definitions/trades.py
oandapyV20/definitions/transactions.py
oandapyV20/endpoints/__init__.py
oandapyV20/endpoints/accounts.py
oandapyV20/endpoints/apirequest.py
oandapyV20/endpoints/decorators.py
oandapyV20/endpoints/forexlabs.py
oandapyV20/endpoints/instruments.py
oandapyV20/endpoints/orders.py
oandapyV20/endpoints/positions.py
oandapyV20/endpoints/pricing.py
oandapyV20/endpoints/trades.py
oandapyV20/endpoints/transactions.py
oandapyV20/endpoints/responses/__init__.py
oandapyV20/endpoints/responses/accounts.py
oandapyV20/endpoints/responses/forexlabs.py
oandapyV20/endpoints/responses/instruments.py
oandapyV20/endpoints/responses/orders.py
oandapyV20/endpoints/responses/positions.py
oandapyV20/endpoints/responses/pricing.py
oandapyV20/endpoints/responses/trades.py
oandapyV20/endpoints/responses/transactions.py
oandapyV20/types/__init__.py
oandapyV20/types/types.py
oandapyV20-0.7.1.dist-info/LICENSE.md
oandapyV20-0.7.1.dist-info/METADATA
oandapyV20-0.7.1.dist-info/WHEEL
oandapyV20-0.7.1.dist-info/entry_points.txt
oandapyV20-0.7.1.dist-info/top_level.txt
oandapyV20-0.7.1.dist-info/RECORD
