Metadata-Version: 2.1
Name: oandapyV20
Version: 0.7.1
Summary: Python wrapper for the OANDA REST-V20 API
Home-page: http://github.com/hootnot/oanda-api-v20
Author: F. Brekeveld
Author-email: f.brekeveld@gmail.com
License: MIT
Keywords: OANDA FOREX/CFD wrapper REST-V20 API
Platform: UNKNOWN
Classifier: Programming Language :: Python
Classifier: License :: OSI Approved :: MIT License
Classifier: Intended Audience :: Developers
Classifier: Intended Audience :: Financial and Insurance Industry
Classifier: Operating System :: OS Independent
Classifier: Development Status :: 3 - Alpha
Classifier: Topic :: Software Development :: Libraries :: Python Modules
Classifier: Programming Language :: Python
Classifier: Programming Language :: Python :: 3.6
Classifier: Programming Language :: Python :: 3.7
Classifier: Programming Language :: Python :: 3.8
Classifier: Programming Language :: Python :: 3.9
